tello_asyncio/__init__.py
tello_asyncio/state.py
tello_asyncio/tello.py
tello_asyncio/types.py
tello_asyncio/video.py
tello_asyncio/wifi.py
tello_asyncio-2.1.3.dist-info/LICENSE
tello_asyncio-2.1.3.dist-info/METADATA
tello_asyncio-2.1.3.dist-info/WHEEL
tello_asyncio-2.1.3.dist-info/top_level.txt
tello_asyncio-2.1.3.dist-info/RECORD
