Metadata-Version: 2.1
Name: tello-asyncio
Version: 2.1.3
Summary: Asyncio-based control library for the Tello drone
Home-page: https://github.com/robagar/tello-asyncio
Author: Rob Agar
Author-email: tello_asyncio@fastmail.net
License: LGPL
Project-URL: Documentation, https://tello-asyncio.readthedocs.io/en/latest/
Requires-Python: >=3.6
License-File: LICENSE
